[
  {
    "post_uri": "at://did:plc:e7atmcvv2bblzo6biapuzi35/app.bsky.feed.post/3mejztfsav22t",
    "post_text": "Trump put a hidden tax on almost everything you buy, making it harder to afford essentials and save for the future.",
    "post_createdAt": "2026-02-10T22:40:53.979Z",
    "replyCount": 2,
    "replies_collected": 2,
    "replies": [
      {
        "handle": "lunaticleft.bsky.social",
        "displayName": "Antifahahaha",
        "createdAt": "2026-02-10T22:53:42.798Z",
        "text": "Kirsten Gillibrand pretending to care about affordability. \n\nbsky.app/profile/luna...",
        "likeCount": 0
      },
      {
        "handle": "bloodybarber.bsky.social",
        "displayName": "Charlie",
        "createdAt": "2026-02-10T23:15:56.898Z",
        "text": "When are you going to actually do something?",
        "likeCount": 0
      }
    ]
  },
  {
    "post_uri": "at://did:plc:e7atmcvv2bblzo6biapuzi35/app.bsky.feed.post/3meemz3mvpk2c",
    "post_text": "Older Americans are \u201cunretiring\u201d because of high living costs. Working families can't afford basic necessities because of the Trump Tariff Tax. And health care premiums are through the roof because Trump refused to extend the enhanced ACA tax credits.\n\nA sad reality under Trump.",
    "post_createdAt": "2026-02-08T19:08:07.309Z",
    "replyCount": 5,
    "replies_collected": 5,
    "replies": [
      {
        "handle": "lunaticleft.bsky.social",
        "displayName": "Antifahahaha",
        "createdAt": "2026-02-08T19:20:22.675Z",
        "text": "Genocidal Dems Dems all on the same page again today. Hammer home the high cost of survival for the commoners. Don't look at us, it's the other team that's bad. \n\nWe see through your bullshit. Genocidal uniparty\nbsky.app/profile/luna...",
        "likeCount": 0
      },
      {
        "handle": "dodgeintercept1.bsky.social",
        "displayName": "The Wraith X",
        "createdAt": "2026-02-09T20:21:32.403Z",
        "text": "bsky.app/profile/reic...",
        "likeCount": 0
      },
      {
        "handle": "pookymedia.bsky.social",
        "displayName": "Pooky Amsterdam",
        "createdAt": "2026-02-08T19:14:03.165Z",
        "text": "Your voice is so important Senator, and while this is true, can you stand up a little more and more vocally against this regime? We know people are voting against their own self- interests all the time. \nWhere is your support against the SAVE Act? \nSpeak out about accountability for DHS!\nSpeak UP",
        "likeCount": 0
      },
      {
        "handle": "bloodybarber.bsky.social",
        "displayName": "Charlie",
        "createdAt": "2026-02-08T20:42:20.283Z",
        "text": "Do something",
        "likeCount": 0
      },
      {
        "handle": "lkc2025.bsky.social",
        "displayName": "Lee cheers Olympic athletes\u2019 free speech | \u274c\ud83d\udc51\u274c\ud83e\uddca",
        "createdAt": "2026-02-10T16:34:03.973Z",
        "text": "Please say something about death camps. couriernewsroom.com/news/map-ice...",
        "likeCount": 0
      }
    ]
  },
  {
    "post_uri": "at://did:plc:e7atmcvv2bblzo6biapuzi35/app.bsky.feed.post/3mecaj63hvs2p",
    "post_text": "Congressional Republicans are keeping Americans from getting the health care they need.",
    "post_createdAt": "2026-02-07T20:19:08.632Z",
    "replyCount": 6,
    "replies_collected": 6,
    "replies": [
      {
        "handle": "guy-montag.bsky.social",
        "displayName": "",
        "createdAt": "2026-02-07T20:31:02.022Z",
        "text": "Do something. Start by getting @schumer.senate.gov to resign",
        "likeCount": 0
      },
      {
        "handle": "lallberry.bsky.social",
        "displayName": "",
        "createdAt": "2026-02-08T04:55:58.232Z",
        "text": "Maybe you should've thought about the consequences of voting YES on so many of his despicable and unqualified nominees.\n\nSpare me your faux outrage \n\nEnabler",
        "likeCount": 0
      },
      {
        "handle": "millennialmusings.bsky.social",
        "displayName": "Dave",
        "createdAt": "2026-02-07T21:30:28.927Z",
        "text": "Good thing @democrats.senate.gov voted to end last year\u2019s shutdown over a *promise* from Republicans to vote on ACA subsidies, right?",
        "likeCount": 1
      },
      {
        "handle": "nycrogue.bsky.social",
        "displayName": "",
        "createdAt": "2026-02-08T17:10:31.711Z",
        "text": "Oh! You're still alive. \n\nHard to know given that we don't see you out there doing anything while Democracy burns.",
        "likeCount": 0
      },
      {
        "handle": "pcccar.bsky.social",
        "displayName": "Maybe She's Born With It, Maybe It's Clinical Depression",
        "createdAt": "2026-02-07T20:42:13.198Z",
        "text": "Was waiting to post about your support of genocide.  I warned you to quit gaslighting us about the Republicans are the ones for the healthcare failure. That's not the full truth and you know it.  You will be voted out for your crimes against humanity.",
        "likeCount": 0
      },
      {
        "handle": "trickledownfailed.bsky.social",
        "displayName": "",
        "createdAt": "2026-02-07T20:29:14.310Z",
        "text": "Congressional Republicans are an embarrassment to themselves, the positions they hold, to the world & to all of humanity who live in & cherish a civilized society\u203c\ufe0f",
        "likeCount": 0
      }
    ]
  },
  {
    "post_uri": "at://did:plc:e7atmcvv2bblzo6biapuzi35/app.bsky.feed.post/3me7xjpgygc22",
    "post_text": "At a time when New Yorkers are already being crushed by high costs under the Trump tariffs, the president continues to put his own narcissism over the good-paying union jobs this project provides and the extraordinary economic impact the Gateway tunnel will bring.\n\nUnbelievable.",
    "post_createdAt": "2026-02-06T22:33:03.683Z",
    "replyCount": 7,
    "replies_collected": 7,
    "replies": [
      {
        "handle": "otabrabgam.bsky.social",
        "displayName": "Michael B.",
        "createdAt": "2026-02-06T22:49:23.774Z",
        "text": "What will you ever do about it? Strongly worded tweets? What a bunch of losers",
        "likeCount": 2
      },
      {
        "handle": "lunaticleft.bsky.social",
        "displayName": "Antifahahaha",
        "createdAt": "2026-02-06T22:51:44.572Z",
        "text": "What's that about narcissism? Your party chose to keep banking AIPAC blood money over beating Trump.\n\nThis entire shitshow is on genocide profiteering Democrats like yourself.",
        "likeCount": 1
      },
      {
        "handle": "lallberry.bsky.social",
        "displayName": "",
        "createdAt": "2026-02-07T00:51:41.172Z",
        "text": "Maybe you should've thought about the consequences of voting YES on so many of his despicable and unqualified nominees.\n\nSpare me your faux outrage.\n\nEnabler",
        "likeCount": 1
      },
      {
        "handle": "p0rtiab00.bsky.social",
        "displayName": "p0rtiaB00",
        "createdAt": "2026-02-06T22:42:04.592Z",
        "text": "And you not only are doing nothing to fight back, and will never favor holding these criminals responsible. NY21 ex-Democrat, thanks to you and Schumer.",
        "likeCount": 1
      },
      {
        "handle": "bloodybarber.bsky.social",
        "displayName": "Charlie",
        "createdAt": "2026-02-06T22:53:02.341Z",
        "text": "Do something. Anything. Please.",
        "likeCount": 2
      },
      {
        "handle": "stgingersnap.bsky.social",
        "displayName": "StGingersnap",
        "createdAt": "2026-02-07T01:37:46.145Z",
        "text": "We know it's not just his narcissism. Putin has dirt on Trump via  Epstein. \nTrump is destroying us by order of Putin.\n#LockHimUp",
        "likeCount": 0
      },
      {
        "handle": "beverlysutphin.bsky.social",
        "displayName": "Beverly Sutphin",
        "createdAt": "2026-02-07T19:46:27.824Z",
        "text": "Do you know what\u2019s unbelievable? Watching you wring your hands over Trump\u2019s tariffs while refusing to actually use your power to stop them. Statements aren\u2019t leadership. If you cared, you\u2019d be fighting to rein in Trump\u2019s tariff authority instead of letting working people keep paying the price.",
        "likeCount": 0
      }
    ]
  },
  {
    "post_uri": "at://did:plc:e7atmcvv2bblzo6biapuzi35/app.bsky.feed.post/3me5kbi6mrs27",
    "post_text": "Americans are worried about costs.\n\nWhat have Trump and Republicans done?\n\nDriven up the cost of health care and basic necessities, leaving families struggling to make ends meet. And now he wants to make housing even more unaffordable.\n\nWorking families deserve a fair shot.",
    "post_createdAt": "2026-02-05T23:30:29.512Z",
    "replyCount": 7,
    "replies_collected": 7,
    "replies": [
      {
        "handle": "dodgeintercept1.bsky.social",
        "displayName": "The Wraith X",
        "createdAt": "2026-02-06T16:36:53.821Z",
        "text": "bsky.app/profile/aoc....",
        "likeCount": 0
      },
      {
        "handle": "bloodybarber.bsky.social",
        "displayName": "Charlie",
        "createdAt": "2026-02-06T02:56:24.059Z",
        "text": "Do. Something.",
        "likeCount": 0
      },
      {
        "handle": "seatown4me.bsky.social",
        "displayName": "",
        "createdAt": "2026-02-06T06:51:43.254Z",
        "text": "Working families deserve not to be terrorized by lawless thugs. Don\u2019t cave, Kirsten. Don\u2019t agree to split out ICE from rest of DHS funding bill. It\u2019s your only leverage.",
        "likeCount": 0
      },
      {
        "handle": "pcccar.bsky.social",
        "displayName": "Maybe She's Born With It, Maybe It's Clinical Depression",
        "createdAt": "2026-02-06T01:36:10.280Z",
        "text": "They've done these things with NAZI DEMOCRAT PEDOPHILE SUPPORTING help\u2757\ufe0fRemember the last shutdown and these Regime supporters\ud83d\udc47",
        "likeCount": 0
      },
      {
        "handle": "beverlysutphin.bsky.social",
        "displayName": "Beverly Sutphin",
        "createdAt": "2026-02-06T01:28:10.548Z",
        "text": "You say \u201cworking families deserve a fair shot,\u201d but your own constituents can\u2019t even get a meeting. Costs are up, people are hurting\u2014and you refuse to face them. What will it take for you to schedule a real town hall in NYC and actually listen for once?",
        "likeCount": 0
      },
      {
        "handle": "lkc2025.bsky.social",
        "displayName": "Lee cheers Olympic athletes\u2019 free speech | \u274c\ud83d\udc51\u274c\ud83e\uddca",
        "createdAt": "2026-02-10T16:34:22.671Z",
        "text": "Please say something about death camps. couriernewsroom.com/news/map-ice...",
        "likeCount": 0
      },
      {
        "handle": "arrdubya.bsky.social",
        "displayName": "Arr Dubya",
        "createdAt": "2026-02-05T23:51:57.286Z",
        "text": "",
        "likeCount": 0
      }
    ]
  },
  {
    "post_uri": "at://did:plc:e7atmcvv2bblzo6biapuzi35/app.bsky.feed.post/3me2upfqgnk2k",
    "post_text": "President Trump and his \u201cagents\u201d don't belong anywhere near vote counting.\n\nThat responsibility is constitutionally guaranteed to the states.",
    "post_createdAt": "2026-02-04T21:59:14.916Z",
    "replyCount": 6,
    "replies_collected": 6,
    "replies": [
      {
        "handle": "lallberry.bsky.social",
        "displayName": "",
        "createdAt": "2026-02-05T01:18:51.641Z",
        "text": "Maybe you should've thought about the consequences of voting YES on so many of his despicable and unqualified nominees.\n\nSpare me your faux outrage.\n\nEnabler",
        "likeCount": 2
      },
      {
        "handle": "peonmusk.bsky.social",
        "displayName": "Cheat The Rich !",
        "createdAt": "2026-02-05T20:46:43.942Z",
        "text": "Nice work. \n\nYou deregulated and legitimated crypto just in time to watch all those retail investors get crushed. \n \nWill you testify with your crypto criminal Bros when the fraud trials start?\n\nUnindicted Co-Conspirator # 1, perhaps?\n\nHope the sweet, sweet campaign contributions were worth it.",
        "likeCount": 0
      },
      {
        "handle": "steeney.bsky.social",
        "displayName": "",
        "createdAt": "2026-02-04T22:38:24.443Z",
        "text": "Did you hear Leavitt \u201che believes in the constitution BUT\u2026\u201d",
        "likeCount": 0
      },
      {
        "handle": "blammo.bsky.social",
        "displayName": "",
        "createdAt": "2026-02-05T20:21:57.199Z",
        "text": "Please never post about an issue unless you plan to put at least as much work into addressing it as you put into providing regulatory giveaways to crypto companies.\n\n(Your communications team is one of the worst in politics)",
        "likeCount": 3
      },
      {
        "handle": "craigerflights.bsky.social",
        "displayName": "craiger",
        "createdAt": "2026-02-05T15:17:49.369Z",
        "text": "You don\u2019t belong anywhere near this \u201cprayer breakfast\u201d obscenity. Why are all the NY (D) senators such garbage?",
        "likeCount": 1
      },
      {
        "handle": "beverlysutphin.bsky.social",
        "displayName": "Beverly Sutphin",
        "createdAt": "2026-02-06T01:30:37.489Z",
        "text": "Enough with the tweets and press releases. When are you actually going to do something? While you posture online, you keep sending more money to fund the Gaza genocide and avoid real accountability at home. Governing takes more than statements \u2014 it takes action.",
        "likeCount": 0
      }
    ]
  },
  {
    "post_uri": "at://did:plc:e7atmcvv2bblzo6biapuzi35/app.bsky.feed.post/3me2rcz3hdc23",
    "post_text": "Trump promised lower prices.\n\nWhat we are getting: Higher grocery prices, higher health care premiums, higher energy prices, and now higher housing prices too.",
    "post_createdAt": "2026-02-04T20:58:37.766Z",
    "replyCount": 4,
    "replies_collected": 4,
    "replies": [
      {
        "handle": "lallberry.bsky.social",
        "displayName": "",
        "createdAt": "2026-02-05T01:23:23.883Z",
        "text": "Maybe you should've thought about the consequences of voting YES on so many of his despicable and unqualified nominees.\n\nSpare me your faux outrage.\n\nEnabler",
        "likeCount": 0
      },
      {
        "handle": "groovycityexpress.bsky.social",
        "displayName": "Living Person",
        "createdAt": "2026-02-04T21:09:27.841Z",
        "text": "Abolish ICE or resign. They are murdering citizens in the streets",
        "likeCount": 0
      },
      {
        "handle": "bloodybarber.bsky.social",
        "displayName": "Charlie",
        "createdAt": "2026-02-04T21:52:49.560Z",
        "text": "Do something!",
        "likeCount": 0
      },
      {
        "handle": "beverlysutphin.bsky.social",
        "displayName": "Beverly Sutphin",
        "createdAt": "2026-02-06T01:32:23.644Z",
        "text": "All tweets, no action. Prices keep climbing and all you offer are posts and talking points. Start doing something for the people you represent \u2014 though I won\u2019t hold my breath.",
        "likeCount": 0
      }
    ]
  },
  {
    "post_uri": "at://did:plc:e7atmcvv2bblzo6biapuzi35/app.bsky.feed.post/3me2ofvn67c2s",
    "post_text": "Trump First, America Last.",
    "post_createdAt": "2026-02-04T20:06:33.589Z",
    "replyCount": 7,
    "replies_collected": 7,
    "replies": [
      {
        "handle": "lunaticleft.bsky.social",
        "displayName": "Antifahahaha",
        "createdAt": "2026-02-04T22:37:50.872Z",
        "text": "Kirsten and her Democratic Party First, Palestine and America Last.",
        "likeCount": 2
      },
      {
        "handle": "groovycityexpress.bsky.social",
        "displayName": "Living Person",
        "createdAt": "2026-02-04T21:14:16.788Z",
        "text": "No plan from Gillibrand. RESIGN",
        "likeCount": 2
      },
      {
        "handle": "fullyautomatedluxury.com",
        "displayName": "Fully Automated",
        "createdAt": "2026-02-04T20:07:57.189Z",
        "text": "No Action Item\n\"X is Y so I will Z\"",
        "likeCount": 2
      },
      {
        "handle": "decib.bsky.social",
        "displayName": "",
        "createdAt": "2026-02-04T20:10:09.497Z",
        "text": "What\u2019s the plan? What legislation is being proposed to stop the grift? What laws are being passed to help us regulate folk? How about repealing Citizens United? How about Universal Healthcare which is proven in other countries to increase access for all while cutting costs?",
        "likeCount": 1
      },
      {
        "handle": "oatsdad.bsky.social",
        "displayName": "Colin Jacobson",
        "createdAt": "2026-02-04T20:47:41.000Z",
        "text": "Why don't Dems do more to spotlight this massive corruption?",
        "likeCount": 1
      },
      {
        "handle": "blammo.bsky.social",
        "displayName": "",
        "createdAt": "2026-02-05T20:24:16.230Z",
        "text": "You co-sponsored the Genius Act, which created the lax regulatory framework that enabled Trump\u2019s crypto scam company to reap billions.\n\nYou also clearly serve big donor money above all else while putting zero effort into actually fighting corruption.\n\nYou are on of them, not one of us.",
        "likeCount": 0
      },
      {
        "handle": "beverlysutphin.bsky.social",
        "displayName": "Beverly Sutphin",
        "createdAt": "2026-02-06T01:34:02.627Z",
        "text": "\u201cTrump First, America Last.\u201d Cool slogan. What the fuck are you actually going to do about it? Another tweet? Another press release? Or are you too busy hanging out with Timothy Dolan to bother doing your job?",
        "likeCount": 0
      }
    ]
  },
  {
    "post_uri": "at://did:plc:e7atmcvv2bblzo6biapuzi35/app.bsky.feed.post/3me2lekmjwk2n",
    "post_text": "Shameful.",
    "post_createdAt": "2026-02-04T19:12:07.256Z",
    "replyCount": 9,
    "replies_collected": 9,
    "replies": [
      {
        "handle": "spin4srv.bsky.social",
        "displayName": "Midnight Train To Georgia On My Mind",
        "createdAt": "2026-02-04T19:24:58.494Z",
        "text": "Please tell us what you are doing and what you will do about it.  That\u2019s what people want to hear.",
        "likeCount": 2
      },
      {
        "handle": "lunaticleft.bsky.social",
        "displayName": "Antifahahaha",
        "createdAt": "2026-02-04T19:31:11.527Z",
        "text": "Kirsten Gillibrand won't apologize for profiting from and funding the GENOCIDE that ensured Trump's return.\n\nShameful.",
        "likeCount": 1
      },
      {
        "handle": "emmemmoh.bsky.social",
        "displayName": "",
        "createdAt": "2026-02-04T19:22:53.050Z",
        "text": "That\u2019s all you got?! What the fuck!",
        "likeCount": 3
      },
      {
        "handle": "enigmasama.bsky.social",
        "displayName": "Quinn",
        "createdAt": "2026-02-04T23:23:37.175Z",
        "text": "He doesn't need to apologize to answer for it.",
        "likeCount": 0
      },
      {
        "handle": "peonmusk.bsky.social",
        "displayName": "Cheat The Rich !",
        "createdAt": "2026-02-04T19:47:30.798Z",
        "text": "Dear Social Media Intern -\n\nAs a graduate of a New York based institution of higher learning, we KNOW you\u2019ve got better stuff than this. \n\nInstead of posting \u201cSky Insists on Being Blue\u201d post about Kirsten\u2019s accomplishments. \n\nSurely \u201cConstituent Services\u201d can provide some ideas ?\n\nOr not\u2026.",
        "likeCount": 2
      },
      {
        "handle": "oatsdad.bsky.social",
        "displayName": "Colin Jacobson",
        "createdAt": "2026-02-04T21:03:23.228Z",
        "text": "You could apply \"shameful\" to basically everything JD does.",
        "likeCount": 0
      },
      {
        "handle": "bloodybarber.bsky.social",
        "displayName": "Charlie",
        "createdAt": "2026-02-04T19:20:51.274Z",
        "text": "I mean, you won't apologize for being worthless. You're both politicians. Of course you both suck.",
        "likeCount": 2
      },
      {
        "handle": "beverlysutphin.bsky.social",
        "displayName": "Beverly Sutphin",
        "createdAt": "2026-02-06T01:36:06.020Z",
        "text": "Yeah it is but you\u2019re the shameful one. You clutch your pearls over words while refusing to take real action, refusing to face your constituents, and continuing to fund violence with your votes. Spare us the performative outrage\u2014do your job for once instead of tweeting about it.",
        "likeCount": 0
      },
      {
        "handle": "trickledownfailed.bsky.social",
        "displayName": "",
        "createdAt": "2026-02-04T19:21:16.280Z",
        "text": "This despicable sleaze bag is just sending more of us to the voting booth\u203c\ufe0f",
        "likeCount": 0
      }
    ]
  },
  {
    "post_uri": "at://did:plc:e7atmcvv2bblzo6biapuzi35/app.bsky.feed.post/3me24gscaps2z",
    "post_text": "No. In America, voters decide the results of elections.",
    "post_createdAt": "2026-02-04T14:44:56.288Z",
    "replyCount": 7,
    "replies_collected": 7,
    "replies": [
      {
        "handle": "lunaticleft.bsky.social",
        "displayName": "Antifahahaha",
        "createdAt": "2026-02-04T15:02:22.457Z",
        "text": "Genocide profiteering, ICE funding Democrats like Kirsten Gillibrand and Kamala Harris are out of power because there is no \"lesser\" evil. Just evil. And 90 million potential voters aren't buying.",
        "likeCount": 1
      },
      {
        "handle": "emmemmoh.bsky.social",
        "displayName": "",
        "createdAt": "2026-02-04T15:05:26.371Z",
        "text": "So, what\u2019s the fucking plan to bolster the elections, @kirstengillibrand.bsky.social ?",
        "likeCount": 2
      },
      {
        "handle": "peonmusk.bsky.social",
        "displayName": "Cheat The Rich !",
        "createdAt": "2026-02-04T15:17:34.665Z",
        "text": "You forgot to promise that the next the Dems have the White House, Senate and House of Representatives they will promptly pass an updated version of the voting rights act.",
        "likeCount": 0
      },
      {
        "handle": "bloodybarber.bsky.social",
        "displayName": "Charlie",
        "createdAt": "2026-02-04T14:51:04.790Z",
        "text": "DO SOMETHING!",
        "likeCount": 1
      },
      {
        "handle": "stgingersnap.bsky.social",
        "displayName": "StGingersnap",
        "createdAt": "2026-02-04T14:58:12.936Z",
        "text": "#ArrestHimNow",
        "likeCount": 0
      },
      {
        "handle": "tombeckett.bsky.social",
        "displayName": "",
        "createdAt": "2026-02-04T16:13:47.879Z",
        "text": "In truth, monied interests decide the results of elections. Your biggest contributor and the reason you never mention the genocide or Trump\u2019s illegal supplies to Israel, is AIPAC which is loaded for 2026 gives 10s of millions to Dem tools like you www.nytimes.com/2026/02/01/u...",
        "likeCount": 0
      },
      {
        "handle": "trickledownfailed.bsky.social",
        "displayName": "",
        "createdAt": "2026-02-04T14:48:13.874Z",
        "text": "700 ICE goons out of Minnesota. This is what happens when we kick them in the balls. \u203c\ufe0f\n2/4:  already today\ud83d\udd3dHang tough, not 1 Dem vote. \u203c\ufe0fHow soon bf they fire randomly into protesters?",
        "likeCount": 0
      }
    ]
  }
]